README.md
setup.py
Supycap/__init__.py
Supycap.egg-info/PKG-INFO
Supycap.egg-info/SOURCES.txt
Supycap.egg-info/dependency_links.txt
Supycap.egg-info/requires.txt
Supycap.egg-info/top_level.txt
Supycap/cc_analysis/__init__.py
Supycap/cc_analysis/glob_analysis.py
Supycap/cc_analysis/load_capacitor.py
Supycap/cc_analysis/supercap.py
Supycap/cc_analysis/utilities.py
Supycap/cc_analysis/cccap/__init__.py
Supycap/cc_analysis/cccap/cc_cap.py
Supycap/cc_analysis/cccap/utilities.py
Supycap/cv_analysis/__init__.py
Supycap/cv_analysis/cv_analysis.py
Supycap/cv_analysis/cv_calc.py
Supycap/cv_analysis/utilities.py