Metadata-Version: 2.1
Name: Supycap
Version: 2.2
Summary: A python library for electrochemical analysis of supercapacitors
Home-page: https://github.com/AdaYuanChen/Supycap
Author: Ada Yuan Chen
Author-email: yuan.chen18@imperial.ac.uk
License: UNKNOWN
Platform: any
Classifier: Programming Language :: Python :: 3
Classifier: License :: OSI Approved :: MIT License
Classifier: Operating System :: OS Independent
